{
  "get": "fixtures",
  "parameters": {
    "date": "2025-05-29",
    "timezone": "Asia/Riyadh"
  },
  "errors": [],
  "results": 260,
  "paging": {
    "current": 1,
    "total": 1
  },
  "response": [
    {
      "fixture": {
        "id": 1342874,
        "referee": null,
        "timezone": "Asia/Riyadh",
        "date": "2025-05-29T14:00:00+03:00",
        "timestamp": 1748516400,
        "periods": {
          "first": null,
          "second": null
        },
        "venue": {
          "id": 8011,
          "name": "Torslandavallen",
          "city": "Torslanda"
        },
        "status": {
          "long": "Not Started",
          "short": "NS",
          "elapsed": null,
          "extra": null
        }
      },
      "league": {
        "id": 564,
        "name": "Ettan - Södra",
        "country": "Sweden",
        "logo": "https://media.api-sports.io/football/leagues/564.png",
        "flag": "https://media.api-sports.io/flags/se.svg",
        "season": 2025,
        "round": "Södra - 10",
        "standings": true
      },
      "teams": {
        "home": {
          "id": 12620,
          "name": "Torslanda",
          "logo": "https://media.api-sports.io/football/teams/12620.png",
          "winner": null
        },
        "away": {
          "id": 21435,
          "name": "Ariana",
          "logo": "https://media.api-sports.io/football/teams/21435.png",
          "winner": null
        }
      },
      "goals": {
        "home": null,
        "away": null
      },
      "score": {
        "halftime": {
          "home": null,
          "away": null
        },
        "fulltime": {
          "home": null,
          "away": null
        },
        "extratime": {
          "home": null,
          "away": null
        },
        "penalty": {
          "home": null,
          "away": null
        }
      }
    },
    {
      "fixture": {
        "id": 1342875,
        "referee": null,
        "timezone": "Asia/Riyadh",
        "date": "2025-05-29T17:00:00+03:00",
        "timestamp": 1748527200,
        "periods": {
          "first": null,
          "second": null
        },
        "venue": {
          "id": 4898,
          "name": "Edsborgs IP",
          "city": "Trollhättan"
        },
        "status": {
          "long": "Not Started",
          "short": "NS",
          "elapsed": null,
          "extra": null
        }
      },
      "league": {
        "id": 564,
        "name": "Ettan - Södra",
        "country": "Sweden",
        "logo": "https://media.api-sports.io/football/leagues/564.png",
        "flag": "https://media.api-sports.io/flags/se.svg",
        "season": 2025,
        "round": "Södra - 10",
        "standings": true
      },
      "teams": {
        "home": {
          "id": 6702,
          "name": "Trollhättan",
          "logo": "https://media.api-sports.io/football/teams/6702.png",
          "winner": null
        },
        "away": {
          "id": 12601,
          "name": "Olympic",
          "logo": "https://media.api-sports.io/football/teams/12601.png",
          "winner": null
        }
      },
      "goals": {
        "home": null,
        "away": null
      },
      "score": {
        "halftime": {
          "home": null,
          "away": null
        },
        "fulltime": {
          "home": null,
          "away": null
        },
        "extratime": {
          "home": null,
          "away": null
        },
        "penalty": {
          "home": null,
          "away": null
        }
      }
    },
    {
      "fixture": {
        "id": 1342876,
        "referee": null,
        "timezone": "Asia/Riyadh",
        "date": "2025-05-29T17:00:00+03:00",
        "timestamp": 1748527200,
        "periods": {
          "first": null,
          "second": null
        },
        "venue": {
          "id": 1507,
          "name": "Borås Arena",
          "city": "Borås"
        },
        "status": {
          "long": "Not Started",
          "short": "NS",
          "elapsed": null,
          "extra": null
        }
      },
      "league": {
        "id": 564,
        "name": "Ettan - Södra",
        "country": "Sweden",
        "logo": "https://media.api-sports.io/football/leagues/564.png",
        "flag": "https://media.api-sports.io/flags/se.svg",
        "season": 2025,
        "round": "Södra - 10",
        "standings": true
      },
      "teams": {
        "home": {
          "id": 2173,
          "name": "Norrby IF",
          "logo": "https://media.api-sports.io/football/teams/2173.png",
          "winner": null
        },
        "away": {
          "id": 2168,
          "name": "Angelholms FF",
          "logo": "https://media.api-sports.io/football/teams/2168.png",
          "winner": null
        }
      },
      "goals": {
        "home": null,
        "away": null
      },
      "score": {
        "halftime": {
          "home": null,
          "away": null
        },
        "fulltime": {
          "home": null,
          "away": null
        },
        "extratime": {
          "home": null,
          "away": null
        },
        "penalty": {
          "home": null,
          "away": null
        }
      }
    },
    {
      "fixture": {
        "id": 1342877,
        "referee": null,
        "timezone": "Asia/Riyadh",
        "date": "2025-05-29T17:00:00+03:00",
        "timestamp": 1748527200,
        "periods": {
          "first": null,
          "second": null
        },
        "venue": {
          "id": 4888,
          "name": "Arena Oskarshamn",
          "city": "Oskarshamn"
        },
        "status": {
          "long": "Not Started",
          "short": "NS",
          "elapsed": null,
          "extra": null
        }
      },
      "league": {
        "id": 564,
        "name": "Ettan - Södra",
        "country": "Sweden",
        "logo": "https://media.api-sports.io/football/leagues/564.png",
        "flag": "https://media.api-sports.io/flags/se.svg",
        "season": 2025,
        "round": "Södra - 10",
        "standings": true
      },
      "teams": {
        "home": {
          "id": 6692,
          "name": "Oskarshamns AIK",
          "logo": "https://media.api-sports.io/football/teams/6692.png",
          "winner": null
        },
        "away": {
          "id": 6694,
          "name": "Rosengård",
          "logo": "https://media.api-sports.io/football/teams/6694.png",
          "winner": null
        }
      },
      "goals": {
        "home": null,
        "away": null
      },
      "score": {
        "halftime": {
          "home": null,
          "away": null
        },
        "fulltime": {
          "home": null,
          "away": null
        },
        "extratime": {
          "home": null,
          "away": null
        },
        "penalty": {
          "home": null,
          "away": null
        }
      }
    },
    {
      "fixture": {
        "id": 1375859,
        "referee": null,
        "timezone": "Asia/Riyadh",
        "date": "2025-05-29T21:30:00+03:00",
        "timestamp": 1748543400,
        "periods": {
          "first": null,
          "second": null
        },
        "venue": {
          "id": null,
          "name": "Stade Auguste-Delaune",
          "city": "Reims"
        },
        "status": {
          "long": "Not Started",
          "short": "NS",
          "elapsed": null,
          "extra": null
        }
      },
      "league": {
        "id": 61,
        "name": "Ligue 1",
        "country": "France",
        "logo": "https://media.api-sports.io/football/leagues/61.png",
        "flag": "https://media.api-sports.io/flags/fr.svg",
        "season": 2024,
        "round": "Relegation Round",
        "standings": true
      },
      "teams": {
        "home": {
          "id": 93,
          "name": "Reims",
          "logo": "https://media.api-sports.io/football/teams/93.png",
          "winner": null
        },
        "away": {
          "id": 112,
          "name": "Metz",
          "logo": "https://media.api-sports.io/football/teams/112.png",
          "winner": null
        }
      },
      "goals": {
        "home": null,
        "away": null
      },
      "score": {
        "halftime": {
          "home": null,
          "away": null
        },
        "fulltime": {
          "home": null,
          "away": null
        },
        "extratime": {
          "home": null,
          "away": null
        },
        "penalty": {
          "home": null,
          "away": null
        }
      }
    }
  ]
}